mmbracategories/__init__.py
mmbracategories/mmbracategories.py
mmbracategories-0.1.dist-info/METADATA
mmbracategories-0.1.dist-info/WHEEL
mmbracategories-0.1.dist-info/top_level.txt
mmbracategories-0.1.dist-info/RECORD
